supermodels/__init__.py
supermodels/config.py
supermodels/exceptions.py
supermodels/fields.py
supermodels/logging.py
supermodels/models.py
supermodels/rules.py
supermodels/serdes.py
supermodels/util.py
supermodels-0.1.12.dist-info/WHEEL
supermodels-0.1.12.dist-info/METADATA
supermodels-0.1.12.dist-info/RECORD
